[
  { "title": "Virtual Tutoring (1 hour, @ $50.00)", "category": "Tutoring", "price": 50 },
  { "title": "Virtual Tutoring Package (6 sessions, @ $250.00)", "category": "Tutoring", "price": 250 },
  { "title": "Virtual Tutoring Package (6 sessions - SCHEDULING)", "category": "Tutoring", "price": 0 },

  { "title": "Virtual Tutoring Package (10 sessions, @ $400)", "category": "Tutoring", "price": 400 },
  { "title": "Virtual Tutoring Package (10 sessions - SCHEDULING)", "category": "Tutoring", "price": 0 },

  { "title": "In-Person Tutoring (1 hour, @ $65.00)", "category": "Tutoring", "price": 65 },
  { "title": "In-Person Tutoring (6 sessions, @ $350.00)", "category": "Tutoring", "price": 350 },
  { "title": "In-Person Tutoring (6 sessions - SCHEDULING)", "category": "Tutoring", "price": 0 },

  { "title": "In-Person Tutoring (10 sessions, @ $580.00)", "category": "Tutoring", "price": 580 },
  { "title": "In-Person Tutoring (10 sessions - SCHEDULING)", "category": "Tutoring", "price": 0 },

  { "title": "Third Party Organization (1 hour)", "category": "Tutoring", "price": 0 },
  { "title": "Third Party Organization (In-Person) (1 hour)", "category": "Tutoring", "price": 0 },

  { "title": "United Mentors (1 hour)", "category": "Tutoring", "price": 0 },
  { "title": "United Mentors (In-Person) (1 hour)", "category": "Tutoring", "price": 0 },

  { "title": "Developer Consultation (30 min)", "category": "Technology", "price": 0 }
]
